README
hidapi_enum.py
setup.cfg
setup.py
pyhidapi/__init__.py
pyhidapi/pyhidapi.py
pyhidapi.egg-info/PKG-INFO
pyhidapi.egg-info/SOURCES.txt
pyhidapi.egg-info/dependency_links.txt
pyhidapi.egg-info/top_level.txt