Metadata-Version: 1.1
Name: pyhidapi
Version: 0.0.2
Summary: Python binding for pyhidapi library.
Home-page: http://www.nf6x.net/tags/pyhidapi/
Author: Julian Poschmann
Author-email: nonymus@nonymus.de
License: GPLv3
Download-URL: https://github.com/NF6X/pyhidapi
Platform: UNKNOWN
